{
    "key": "group_61c0870241e2f",
    "title": "Text & Quote",
    "fields": [
        {
            "key": "field_61c087a350e4f",
            "label": "Heading",
            "name": "text_quote_heading",
            "type": "text",
            "instructions": "",
            "required": 0,
            "conditional_logic": 0,
            "wrapper": {
                "width": "",
                "class": "",
                "id": ""
            },
            "default_value": "",
            "placeholder": "",
            "prepend": "",
            "append": "",
            "maxlength": ""
        },
        {
            "key": "field_61c087b350e50",
            "label": "Text",
            "name": "text_quote_text",
            "type": "wysiwyg",
            "instructions": "",
            "required": 1,
            "conditional_logic": 0,
            "wrapper": {
                "width": "",
                "class": "",
                "id": ""
            },
            "default_value": "",
            "tabs": "visual",
            "toolbar": "basic",
            "media_upload": 0,
            "delay": 0
        },
        {
            "key": "field_61c087d150e51",
            "label": "Quote",
            "name": "text_quote_quote",
            "type": "textarea",
            "instructions": "<em>50 Word Limit - text from this field will be trimmed to 50 words, and append an ellipses (&hellip;)<\/em>",
            "required": 1,
            "conditional_logic": 0,
            "wrapper": {
                "width": "",
                "class": "",
                "id": ""
            },
            "default_value": "",
            "placeholder": "",
            "maxlength": "",
            "rows": 2,
            "new_lines": ""
        },
        {
            "key": "field_61c087e450e52",
            "label": "Quote Citation",
            "name": "text_quote_quote_citation",
            "type": "text",
            "instructions": "",
            "required": 1,
            "conditional_logic": 0,
            "wrapper": {
                "width": "",
                "class": "",
                "id": ""
            },
            "default_value": "",
            "placeholder": "",
            "prepend": "",
            "append": "",
            "maxlength": ""
        }
    ],
    "location": [
        [
            {
                "param": "post_type",
                "operator": "==",
                "value": "story"
            }
        ]
    ],
    "menu_order": 0,
    "position": "normal",
    "style": "default",
    "label_placement": "left",
    "instruction_placement": "label",
    "hide_on_screen": "",
    "active": true,
    "description": "",
    "show_in_rest": 0,
    "modified": 1652301231
}